CHANGES.md
MANIFEST.in
README.rst
requirements.txt
setup.py
Gazette.egg-info/PKG-INFO
Gazette.egg-info/SOURCES.txt
Gazette.egg-info/dependency_links.txt
Gazette.egg-info/entry_points.txt
Gazette.egg-info/requires.txt
Gazette.egg-info/top_level.txt
gazette/__init__.py
gazette/api.py
gazette/content_types.py
gazette/models.py
gazette/utils.py
gazette/test/__init__.py
gazette/test/test_api.py
gazette/test/test_models.py
gazette/test/test_types.py
gazette/test/test_utils.py