Metadata-Version: 1.1
Name: Gazette
Version: 1.1.0
Summary: A flexible CMS library that can be added into any app.
Home-page: https://sf.net/p/gazette
Author: Gazette Team
Author-email: UNKNOWN
License: MIT
Platform: UNKNOWN
Classifier: Natural Language :: English
Classifier: Operating System :: OS Independent
